{
  "game": "xocdia",
  "updatedAt": "2026-05-29T22:54:26.443Z",
  "maxHistory": 180,
  "totals": {
    "rounds": 2672,
    "win": 1345,
    "lose": 1327,
    "winRate": 50,
    "profit": 13440000,
    "currentStreak": -1,
    "nextBet": 40000,
    "lastSession": "1616553"
  },
  "state": {
    "loseStreak": 1,
    "predictSide": "LE",
    "localSession": 0,
    "lastRoundKey": "s:1616553",
    "streak": -1
  },
  "history": [
    {
      "session": "1613970",
      "side": "CHAN",
      "label": "CHẴN",
      "value": 2,
      "display": "2-2 ⚪⚪🔴🔴",
      "status": "LOSE",
      "bet": 10000,
      "change": -10000,
      "timestamp": 1780009211872
    },
    {
      "session": "1613971",
      "side": "CHAN",
      "label": "CHẴN",
      "value": 2,
      "display": "2-2 ⚪⚪🔴🔴",
      "status": "WIN",
      "bet": 20000,
      "change": 20000,
      "timestamp": 1780009244894
    },
    {
      "session": "1614085",
      "side": "LE",
      "label": "LẺ",
      "value": 3,
      "display": "3 đỏ 1 trắng 🔴🔴🔴⚪",
      "status": "LOSE",
      "bet": 10000,
      "change": -10000,
      "timestamp": 1780013012570
    },
    {
      "session": "1614086",
      "side": "CHAN",
      "label": "CHẴN",
      "value": 2,
      "display": "2-2 ⚪⚪🔴🔴",
      "status": "WIN",
      "bet": 20000,
      "change": 20000,
      "timestamp": 1780013045378
    },
    {
      "session": "1614087",
      "side": "CHAN",
      "label": "CHẴN",
      "value": 2,
      "display": "2-2 ⚪⚪🔴🔴",
      "status": "WIN",
      "bet": 10000,
      "change": 10000,
      "timestamp": 1780013078165
    },
    {
      "session": "1614367",
      "side": "LE",
      "label": "LẺ",
      "value": 3,
      "display": "3 đỏ 1 trắng 🔴🔴🔴⚪",
      "status": "LOSE",
      "bet": 10000,
      "change": -10000,
      "timestamp": 1780022300678
    },
    {
      "session": "1614368",
      "side": "LE",
      "label": "LẺ",
      "value": 3,
      "display": "3 đỏ 1 trắng 🔴🔴🔴⚪",
      "status": "LOSE",
      "bet": 20000,
      "change": -20000,
      "timestamp": 1780022333605
    },
    {
      "session": "1614369",
      "side": "CHAN",
      "label": "CHẴN",
      "value": 4,
      "display": "4 đỏ 🔴🔴🔴🔴",
      "status": "WIN",
      "bet": 40000,
      "change": 40000,
      "timestamp": 1780022366942
    },
    {
      "session": "1614463",
      "side": "LE",
      "label": "LẺ",
      "value": 1,
      "display": "1 đỏ 3 trắng 🔴⚪⚪⚪",
      "status": "LOSE",
      "bet": 10000,
      "change": -10000,
      "timestamp": 1780025467683
    },
    {
      "session": "1614464",
      "side": "CHAN",
      "label": "CHẴN",
      "value": 2,
      "display": "2-2 ⚪⚪🔴🔴",
      "status": "LOSE",
      "bet": 20000,
      "change": -20000,
      "timestamp": 1780025501005
    },
    {
      "session": "1614595",
      "side": "LE",
      "label": "LẺ",
      "value": 3,
      "display": "3 đỏ 1 trắng 🔴🔴🔴⚪",
      "status": "WIN",
      "bet": 40000,
      "change": 40000,
      "timestamp": 1780029827116
    },
    {
      "session": "1614596",
      "side": "LE",
      "label": "LẺ",
      "value": 3,
      "display": "3 đỏ 1 trắng 🔴🔴🔴⚪",
      "status": "LOSE",
      "bet": 10000,
      "change": -10000,
      "timestamp": 1780029860256
    },
    {
      "session": "1614597",
      "side": "LE",
      "label": "LẺ",
      "value": 1,
      "display": "1 đỏ 3 trắng 🔴⚪⚪⚪",
      "status": "LOSE",
      "bet": 20000,
      "change": -20000,
      "timestamp": 1780029893241
    },
    {
      "session": "1614816",
      "side": "LE",
      "label": "LẺ",
      "value": 1,
      "display": "1 đỏ 3 trắng 🔴⚪⚪⚪",
      "status": "LOSE",
      "bet": 40000,
      "change": -40000,
      "timestamp": 1780037134813
    },
    {
      "session": "1614817",
      "side": "CHAN",
      "label": "CHẴN",
      "value": 2,
      "display": "2-2 ⚪⚪🔴🔴",
      "status": "LOSE",
      "bet": 80000,
      "change": -80000,
      "timestamp": 1780037167710
    },
    {
      "session": "1614862",
      "side": "CHAN",
      "label": "CHẴN",
      "value": 2,
      "display": "2-2 ⚪⚪🔴🔴",
      "status": "LOSE",
      "bet": 160000,
      "change": -160000,
      "timestamp": 1780038655016
    },
    {
      "session": "1614863",
      "side": "CHAN",
      "label": "CHẴN",
      "value": 2,
      "display": "2-2 ⚪⚪🔴🔴",
      "status": "LOSE",
      "bet": 320000,
      "change": -320000,
      "timestamp": 1780038688031
    },
    {
      "session": "1614864",
      "side": "CHAN",
      "label": "CHẴN",
      "value": 2,
      "display": "2-2 ⚪⚪🔴🔴",
      "status": "LOSE",
      "bet": 640000,
      "change": -640000,
      "timestamp": 1780038721127
    },
    {
      "session": "1615007",
      "side": "CHAN",
      "label": "CHẴN",
      "value": 2,
      "display": "2-2 ⚪⚪🔴🔴",
      "status": "LOSE",
      "bet": 1280000,
      "change": -1280000,
      "timestamp": 1780043455739
    },
    {
      "session": "1615008",
      "side": "CHAN",
      "label": "CHẴN",
      "value": 2,
      "display": "2-2 ⚪⚪🔴🔴",
      "status": "LOSE",
      "bet": 2560000,
      "change": -2560000,
      "timestamp": 1780043488985
    },
    {
      "session": "1615009",
      "side": "LE",
      "label": "LẺ",
      "value": 1,
      "display": "1 đỏ 3 trắng 🔴⚪⚪⚪",
      "status": "LOSE",
      "bet": 5120000,
      "change": -5120000,
      "timestamp": 1780043522122
    },
    {
      "session": "1615239",
      "side": "CHAN",
      "label": "CHẴN",
      "value": 2,
      "display": "2-2 ⚪⚪🔴🔴",
      "status": "WIN",
      "bet": 10240000,
      "change": 10240000,
      "timestamp": 1780051154946
    },
    {
      "session": "1615240",
      "side": "LE",
      "label": "LẺ",
      "value": 3,
      "display": "3 đỏ 1 trắng 🔴🔴🔴⚪",
      "status": "LOSE",
      "bet": 10000,
      "change": -10000,
      "timestamp": 1780051188134
    },
    {
      "session": "1615241",
      "side": "CHAN",
      "label": "CHẴN",
      "value": 2,
      "display": "2-2 ⚪⚪🔴🔴",
      "status": "LOSE",
      "bet": 20000,
      "change": -20000,
      "timestamp": 1780051221526
    },
    {
      "session": "1615270",
      "side": "CHAN",
      "label": "CHẴN",
      "value": 2,
      "display": "2-2 ⚪⚪🔴🔴",
      "status": "LOSE",
      "bet": 40000,
      "change": -40000,
      "timestamp": 1780052184796
    },
    {
      "session": "1615271",
      "side": "CHAN",
      "label": "CHẴN",
      "value": 2,
      "display": "2-2 ⚪⚪🔴🔴",
      "status": "LOSE",
      "bet": 80000,
      "change": -80000,
      "timestamp": 1780052217917
    },
    {
      "session": "1615272",
      "side": "CHAN",
      "label": "CHẴN",
      "value": 2,
      "display": "2-2 ⚪⚪🔴🔴",
      "status": "WIN",
      "bet": 160000,
      "change": 160000,
      "timestamp": 1780052251085
    },
    {
      "session": "1615366",
      "side": "CHAN",
      "label": "CHẴN",
      "value": 0,
      "display": "4 trắng ⚪⚪⚪⚪",
      "status": "WIN",
      "bet": 10000,
      "change": 10000,
      "timestamp": 1780055375605
    },
    {
      "session": "1615367",
      "side": "LE",
      "label": "LẺ",
      "value": 3,
      "display": "3 đỏ 1 trắng 🔴🔴🔴⚪",
      "status": "LOSE",
      "bet": 10000,
      "change": -10000,
      "timestamp": 1780055409308
    },
    {
      "session": "1615368",
      "side": "LE",
      "label": "LẺ",
      "value": 1,
      "display": "1 đỏ 3 trắng 🔴⚪⚪⚪",
      "status": "LOSE",
      "bet": 20000,
      "change": -20000,
      "timestamp": 1780055442368
    },
    {
      "session": "1615592",
      "side": "LE",
      "label": "LẺ",
      "value": 1,
      "display": "1 đỏ 3 trắng 🔴⚪⚪⚪",
      "status": "LOSE",
      "bet": 40000,
      "change": -40000,
      "timestamp": 1780062890093
    },
    {
      "session": "1615593",
      "side": "CHAN",
      "label": "CHẴN",
      "value": 2,
      "display": "2-2 ⚪⚪🔴🔴",
      "status": "WIN",
      "bet": 80000,
      "change": 80000,
      "timestamp": 1780062923372
    },
    {
      "session": "1615594",
      "side": "LE",
      "label": "LẺ",
      "value": 1,
      "display": "1 đỏ 3 trắng 🔴⚪⚪⚪",
      "status": "WIN",
      "bet": 10000,
      "change": 10000,
      "timestamp": 1780062956691
    },
    {
      "session": "1615657",
      "side": "LE",
      "label": "LẺ",
      "value": 3,
      "display": "3 đỏ 1 trắng 🔴🔴🔴⚪",
      "status": "WIN",
      "bet": 10000,
      "change": 10000,
      "timestamp": 1780065050821
    },
    {
      "session": "1615658",
      "side": "LE",
      "label": "LẺ",
      "value": 1,
      "display": "1 đỏ 3 trắng 🔴⚪⚪⚪",
      "status": "LOSE",
      "bet": 10000,
      "change": -10000,
      "timestamp": 1780065084086
    },
    {
      "session": "1615941",
      "side": "CHAN",
      "label": "CHẴN",
      "value": 2,
      "display": "2-2 ⚪⚪🔴🔴",
      "status": "WIN",
      "bet": 20000,
      "change": 20000,
      "timestamp": 1780074522773
    },
    {
      "session": "1615942",
      "side": "CHAN",
      "label": "CHẴN",
      "value": 2,
      "display": "2-2 ⚪⚪🔴🔴",
      "status": "LOSE",
      "bet": 10000,
      "change": -10000,
      "timestamp": 1780074557772
    },
    {
      "session": "1615943",
      "side": "CHAN",
      "label": "CHẴN",
      "value": 2,
      "display": "2-2 ⚪⚪🔴🔴",
      "status": "WIN",
      "bet": 20000,
      "change": 20000,
      "timestamp": 1780074593279
    },
    {
      "session": "1615970",
      "side": "LE",
      "label": "LẺ",
      "value": 3,
      "display": "3 đỏ 1 trắng 🔴🔴🔴⚪",
      "status": "LOSE",
      "bet": 10000,
      "change": -10000,
      "timestamp": 1780075574630
    },
    {
      "session": "1615971",
      "side": "CHAN",
      "label": "CHẴN",
      "value": 2,
      "display": "2-2 ⚪⚪🔴🔴",
      "status": "WIN",
      "bet": 20000,
      "change": 20000,
      "timestamp": 1780075611217
    },
    {
      "session": "1616015",
      "side": "LE",
      "label": "LẺ",
      "value": 3,
      "display": "3 đỏ 1 trắng 🔴🔴🔴⚪",
      "status": "LOSE",
      "bet": 10000,
      "change": -10000,
      "timestamp": 1780077203157
    },
    {
      "session": "1616016",
      "side": "LE",
      "label": "LẺ",
      "value": 3,
      "display": "3 đỏ 1 trắng 🔴🔴🔴⚪",
      "status": "WIN",
      "bet": 20000,
      "change": 20000,
      "timestamp": 1780077246631
    },
    {
      "session": "1616214",
      "side": "CHAN",
      "label": "CHẴN",
      "value": 2,
      "display": "2-2 ⚪⚪🔴🔴",
      "status": "LOSE",
      "bet": 10000,
      "change": -10000,
      "timestamp": 1780084015208
    },
    {
      "session": "1616215",
      "side": "CHAN",
      "label": "CHẴN",
      "value": 0,
      "display": "4 trắng ⚪⚪⚪⚪",
      "status": "WIN",
      "bet": 20000,
      "change": 20000,
      "timestamp": 1780084048491
    },
    {
      "session": "1616216",
      "side": "CHAN",
      "label": "CHẴN",
      "value": 2,
      "display": "2-2 ⚪⚪🔴🔴",
      "status": "LOSE",
      "bet": 10000,
      "change": -10000,
      "timestamp": 1780084081536
    },
    {
      "session": "1616243",
      "side": "CHAN",
      "label": "CHẴN",
      "value": 0,
      "display": "4 trắng ⚪⚪⚪⚪",
      "status": "LOSE",
      "bet": 20000,
      "change": -20000,
      "timestamp": 1780084972782
    },
    {
      "session": "1616244",
      "side": "LE",
      "label": "LẺ",
      "value": 3,
      "display": "3 đỏ 1 trắng 🔴🔴🔴⚪",
      "status": "LOSE",
      "bet": 40000,
      "change": -40000,
      "timestamp": 1780085005895
    },
    {
      "session": "1616245",
      "side": "CHAN",
      "label": "CHẴN",
      "value": 2,
      "display": "2-2 ⚪⚪🔴🔴",
      "status": "WIN",
      "bet": 80000,
      "change": 80000,
      "timestamp": 1780085038699
    },
    {
      "session": "1616403",
      "side": "LE",
      "label": "LẺ",
      "value": 3,
      "display": "3 đỏ 1 trắng 🔴🔴🔴⚪",
      "status": "LOSE",
      "bet": 10000,
      "change": -10000,
      "timestamp": 1780090286086
    },
    {
      "session": "1616404",
      "side": "LE",
      "label": "LẺ",
      "value": 3,
      "display": "3 đỏ 1 trắng 🔴🔴🔴⚪",
      "status": "WIN",
      "bet": 20000,
      "change": 20000,
      "timestamp": 1780090319086
    },
    {
      "session": "1616405",
      "side": "LE",
      "label": "LẺ",
      "value": 1,
      "display": "1 đỏ 3 trắng 🔴⚪⚪⚪",
      "status": "WIN",
      "bet": 10000,
      "change": 10000,
      "timestamp": 1780090352044
    },
    {
      "session": "1616447",
      "side": "CHAN",
      "label": "CHẴN",
      "value": 2,
      "display": "2-2 ⚪⚪🔴🔴",
      "status": "LOSE",
      "bet": 10000,
      "change": -10000,
      "timestamp": 1780091741505
    },
    {
      "session": "1616448",
      "side": "CHAN",
      "label": "CHẴN",
      "value": 2,
      "display": "2-2 ⚪⚪🔴🔴",
      "status": "WIN",
      "bet": 20000,
      "change": 20000,
      "timestamp": 1780091774639
    },
    {
      "session": "1616551",
      "side": "CHAN",
      "label": "CHẴN",
      "value": 2,
      "display": "2-2 ⚪⚪🔴🔴",
      "status": "WIN",
      "bet": 10000,
      "change": 10000,
      "timestamp": 1780095199719
    },
    {
      "session": "1616552",
      "side": "CHAN",
      "label": "CHẴN",
      "value": 2,
      "display": "2-2 ⚪⚪🔴🔴",
      "status": "WIN",
      "bet": 10000,
      "change": 10000,
      "timestamp": 1780095232881
    },
    {
      "session": "1616553",
      "side": "CHAN",
      "label": "CHẴN",
      "value": 2,
      "display": "2-2 ⚪⚪🔴🔴",
      "status": "LOSE",
      "bet": 10000,
      "change": -10000,
      "timestamp": 1780095266443
    }
  ]
}