{
  "game": "xocdia",
  "updatedAt": "2026-05-20T05:42:40.501Z",
  "maxHistory": 180,
  "totals": {
    "rounds": 2141,
    "win": 1070,
    "lose": 1071,
    "winRate": 50,
    "profit": 10690000,
    "currentStreak": -1,
    "nextBet": 40000,
    "lastSession": "1581978"
  },
  "state": {
    "loseStreak": 1,
    "predictSide": "CHAN",
    "localSession": 0,
    "lastRoundKey": "s:1581978",
    "streak": -1
  },
  "history": [
    {
      "session": "1579517",
      "side": "LE",
      "label": "LẺ",
      "value": 3,
      "display": "3 đỏ 1 trắng 🔴🔴🔴⚪",
      "status": "LOSE",
      "bet": 20000,
      "change": -20000,
      "timestamp": 1779169363122
    },
    {
      "session": "1579518",
      "side": "CHAN",
      "label": "CHẴN",
      "value": 4,
      "display": "4 đỏ 🔴🔴🔴🔴",
      "status": "WIN",
      "bet": 40000,
      "change": 40000,
      "timestamp": 1779169395978
    },
    {
      "session": "1579542",
      "side": "CHAN",
      "label": "CHẴN",
      "value": 4,
      "display": "4 đỏ 🔴🔴🔴🔴",
      "status": "WIN",
      "bet": 10000,
      "change": 10000,
      "timestamp": 1779170188967
    },
    {
      "session": "1579543",
      "side": "CHAN",
      "label": "CHẴN",
      "value": 0,
      "display": "4 trắng ⚪⚪⚪⚪",
      "status": "LOSE",
      "bet": 10000,
      "change": -10000,
      "timestamp": 1779170222060
    },
    {
      "session": "1579544",
      "side": "LE",
      "label": "LẺ",
      "value": 1,
      "display": "1 đỏ 3 trắng 🔴⚪⚪⚪",
      "status": "WIN",
      "bet": 20000,
      "change": 20000,
      "timestamp": 1779170255128
    },
    {
      "session": "1579854",
      "side": "CHAN",
      "label": "CHẴN",
      "value": 2,
      "display": "2-2 ⚪⚪🔴🔴",
      "status": "LOSE",
      "bet": 10000,
      "change": -10000,
      "timestamp": 1779180551749
    },
    {
      "session": "1579855",
      "side": "LE",
      "label": "LẺ",
      "value": 3,
      "display": "3 đỏ 1 trắng 🔴🔴🔴⚪",
      "status": "WIN",
      "bet": 20000,
      "change": 20000,
      "timestamp": 1779180584853
    },
    {
      "session": "1579856",
      "side": "LE",
      "label": "LẺ",
      "value": 1,
      "display": "1 đỏ 3 trắng 🔴⚪⚪⚪",
      "status": "WIN",
      "bet": 10000,
      "change": 10000,
      "timestamp": 1779180617821
    },
    {
      "session": "1579865",
      "side": "CHAN",
      "label": "CHẴN",
      "value": 4,
      "display": "4 đỏ 🔴🔴🔴🔴",
      "status": "LOSE",
      "bet": 10000,
      "change": -10000,
      "timestamp": 1779180916729
    },
    {
      "session": "1579866",
      "side": "LE",
      "label": "LẺ",
      "value": 1,
      "display": "1 đỏ 3 trắng 🔴⚪⚪⚪",
      "status": "WIN",
      "bet": 20000,
      "change": 20000,
      "timestamp": 1779180949816
    },
    {
      "session": "1579867",
      "side": "CHAN",
      "label": "CHẴN",
      "value": 4,
      "display": "4 đỏ 🔴🔴🔴🔴",
      "status": "LOSE",
      "bet": 10000,
      "change": -10000,
      "timestamp": 1779180982995
    },
    {
      "session": "1580194",
      "side": "CHAN",
      "label": "CHẴN",
      "value": 2,
      "display": "2-2 ⚪⚪🔴🔴",
      "status": "LOSE",
      "bet": 20000,
      "change": -20000,
      "timestamp": 1779191837190
    },
    {
      "session": "1580195",
      "side": "LE",
      "label": "LẺ",
      "value": 3,
      "display": "3 đỏ 1 trắng 🔴🔴🔴⚪",
      "status": "LOSE",
      "bet": 40000,
      "change": -40000,
      "timestamp": 1779191870287
    },
    {
      "session": "1580196",
      "side": "LE",
      "label": "LẺ",
      "value": 1,
      "display": "1 đỏ 3 trắng 🔴⚪⚪⚪",
      "status": "LOSE",
      "bet": 80000,
      "change": -80000,
      "timestamp": 1779191903453
    },
    {
      "session": "1580466",
      "side": "CHAN",
      "label": "CHẴN",
      "value": 2,
      "display": "2-2 ⚪⚪🔴🔴",
      "status": "WIN",
      "bet": 160000,
      "change": 160000,
      "timestamp": 1779200879482
    },
    {
      "session": "1580467",
      "side": "CHAN",
      "label": "CHẴN",
      "value": 2,
      "display": "2-2 ⚪⚪🔴🔴",
      "status": "LOSE",
      "bet": 10000,
      "change": -10000,
      "timestamp": 1779200912807
    },
    {
      "session": "1580468",
      "side": "CHAN",
      "label": "CHẴN",
      "value": 4,
      "display": "4 đỏ 🔴🔴🔴🔴",
      "status": "LOSE",
      "bet": 20000,
      "change": -20000,
      "timestamp": 1779200945710
    },
    {
      "session": "1580784",
      "side": "CHAN",
      "label": "CHẴN",
      "value": 0,
      "display": "4 trắng ⚪⚪⚪⚪",
      "status": "LOSE",
      "bet": 40000,
      "change": -40000,
      "timestamp": 1779211551010
    },
    {
      "session": "1580785",
      "side": "CHAN",
      "label": "CHẴN",
      "value": 4,
      "display": "4 đỏ 🔴🔴🔴🔴",
      "status": "WIN",
      "bet": 80000,
      "change": 80000,
      "timestamp": 1779211584901
    },
    {
      "session": "1580995",
      "side": "CHAN",
      "label": "CHẴN",
      "value": 2,
      "display": "2-2 ⚪⚪🔴🔴",
      "status": "WIN",
      "bet": 10000,
      "change": 10000,
      "timestamp": 1779218822730
    },
    {
      "session": "1580996",
      "side": "LE",
      "label": "LẺ",
      "value": 1,
      "display": "1 đỏ 3 trắng 🔴⚪⚪⚪",
      "status": "LOSE",
      "bet": 10000,
      "change": -10000,
      "timestamp": 1779218855677
    },
    {
      "session": "1581166",
      "side": "LE",
      "label": "LẺ",
      "value": 1,
      "display": "1 đỏ 3 trắng 🔴⚪⚪⚪",
      "status": "LOSE",
      "bet": 20000,
      "change": -20000,
      "timestamp": 1779224472232
    },
    {
      "session": "1581167",
      "side": "LE",
      "label": "LẺ",
      "value": 1,
      "display": "1 đỏ 3 trắng 🔴⚪⚪⚪",
      "status": "WIN",
      "bet": 40000,
      "change": 40000,
      "timestamp": 1779224505151
    },
    {
      "session": "1581168",
      "side": "LE",
      "label": "LẺ",
      "value": 1,
      "display": "1 đỏ 3 trắng 🔴⚪⚪⚪",
      "status": "WIN",
      "bet": 10000,
      "change": 10000,
      "timestamp": 1779224538089
    },
    {
      "session": "1581290",
      "side": "LE",
      "label": "LẺ",
      "value": 3,
      "display": "3 đỏ 1 trắng 🔴🔴🔴⚪",
      "status": "WIN",
      "bet": 10000,
      "change": 10000,
      "timestamp": 1779228564708
    },
    {
      "session": "1581291",
      "side": "CHAN",
      "label": "CHẴN",
      "value": 2,
      "display": "2-2 ⚪⚪🔴🔴",
      "status": "WIN",
      "bet": 10000,
      "change": 10000,
      "timestamp": 1779228597763
    },
    {
      "session": "1581292",
      "side": "CHAN",
      "label": "CHẴN",
      "value": 2,
      "display": "2-2 ⚪⚪🔴🔴",
      "status": "LOSE",
      "bet": 10000,
      "change": -10000,
      "timestamp": 1779228630675
    },
    {
      "session": "1581421",
      "side": "CHAN",
      "label": "CHẴN",
      "value": 0,
      "display": "4 trắng ⚪⚪⚪⚪",
      "status": "LOSE",
      "bet": 20000,
      "change": -20000,
      "timestamp": 1779232895426
    },
    {
      "session": "1581422",
      "side": "CHAN",
      "label": "CHẴN",
      "value": 2,
      "display": "2-2 ⚪⚪🔴🔴",
      "status": "WIN",
      "bet": 40000,
      "change": 40000,
      "timestamp": 1779232929037
    },
    {
      "session": "1581423",
      "side": "CHAN",
      "label": "CHẴN",
      "value": 2,
      "display": "2-2 ⚪⚪🔴🔴",
      "status": "LOSE",
      "bet": 10000,
      "change": -10000,
      "timestamp": 1779232962011
    },
    {
      "session": "1581520",
      "side": "CHAN",
      "label": "CHẴN",
      "value": 2,
      "display": "2-2 ⚪⚪🔴🔴",
      "status": "LOSE",
      "bet": 20000,
      "change": -20000,
      "timestamp": 1779240609048
    },
    {
      "session": "1581521",
      "side": "CHAN",
      "label": "CHẴN",
      "value": 2,
      "display": "2-2 ⚪⚪🔴🔴",
      "status": "WIN",
      "bet": 40000,
      "change": 40000,
      "timestamp": 1779240641965
    },
    {
      "session": "1581522",
      "side": "CHAN",
      "label": "CHẴN",
      "value": 2,
      "display": "2-2 ⚪⚪🔴🔴",
      "status": "WIN",
      "bet": 10000,
      "change": 10000,
      "timestamp": 1779240674877
    },
    {
      "session": "1581877",
      "side": "LE",
      "label": "LẺ",
      "value": 3,
      "display": "3 đỏ 1 trắng 🔴🔴🔴⚪",
      "status": "LOSE",
      "bet": 10000,
      "change": -10000,
      "timestamp": 1779252420094
    },
    {
      "session": "1581878",
      "side": "CHAN",
      "label": "CHẴN",
      "value": 2,
      "display": "2-2 ⚪⚪🔴🔴",
      "status": "WIN",
      "bet": 20000,
      "change": 20000,
      "timestamp": 1779252453195
    },
    {
      "session": "1581879",
      "side": "LE",
      "label": "LẺ",
      "value": 3,
      "display": "3 đỏ 1 trắng 🔴🔴🔴⚪",
      "status": "WIN",
      "bet": 10000,
      "change": 10000,
      "timestamp": 1779252486194
    },
    {
      "session": "1581976",
      "side": "CHAN",
      "label": "CHẴN",
      "value": 2,
      "display": "2-2 ⚪⚪🔴🔴",
      "status": "LOSE",
      "bet": 10000,
      "change": -10000,
      "timestamp": 1779255694614
    },
    {
      "session": "1581977",
      "side": "LE",
      "label": "LẺ",
      "value": 3,
      "display": "3 đỏ 1 trắng 🔴🔴🔴⚪",
      "status": "WIN",
      "bet": 20000,
      "change": 20000,
      "timestamp": 1779255727414
    },
    {
      "session": "1581978",
      "side": "LE",
      "label": "LẺ",
      "value": 1,
      "display": "1 đỏ 3 trắng 🔴⚪⚪⚪",
      "status": "LOSE",
      "bet": 10000,
      "change": -10000,
      "timestamp": 1779255760501
    }
  ]
}